pulp/__init__.py
pulp/constants.py
pulp/mps_lp.py
pulp/pulp.py
pulp/sparse.py
pulp/utilities.py
pulp/apis/__init__.py
pulp/apis/choco_api.py
pulp/apis/coin_api.py
pulp/apis/copt_api.py
pulp/apis/core.py
pulp/apis/cplex_api.py
pulp/apis/cuopt_api.py
pulp/apis/glpk_api.py
pulp/apis/gurobi_api.py
pulp/apis/highs_api.py
pulp/apis/mipcl_api.py
pulp/apis/mosek_api.py
pulp/apis/sas_api.py
pulp/apis/scip_api.py
pulp/apis/xpress_api.py
pulp/solverdir/__init__.py
pulp/solverdir/cbc/linux/arm64/__init__.py
pulp/solverdir/cbc/linux/arm64/cbc
pulp/solverdir/cbc/linux/arm64/coin-license.txt
pulp/solverdir/cbc/linux/i32/__init__.py
pulp/solverdir/cbc/linux/i32/cbc
pulp/solverdir/cbc/linux/i32/coin-license.txt
pulp/solverdir/cbc/linux/i64/__init__.py
pulp/solverdir/cbc/linux/i64/cbc
pulp/solverdir/cbc/linux/i64/coin-license.txt
pulp/solverdir/cbc/osx/i64/__init__.py
pulp/solverdir/cbc/osx/i64/cbc
pulp/solverdir/cbc/osx/i64/coin-license.txt
pulp/solverdir/cbc/win/i32/__init__.py
pulp/solverdir/cbc/win/i32/cbc.exe
pulp/solverdir/cbc/win/i32/coin-license.txt
pulp/solverdir/cbc/win/i64/__init__.py
pulp/solverdir/cbc/win/i64/cbc.exe
pulp/solverdir/cbc/win/i64/coin-license.txt
pulp/tests/__init__.py
pulp/tests/bin_packing_problem.py
pulp/tests/run_tests.py
pulp/tests/test_examples.py
pulp/tests/test_gurobipy_env.py
pulp/tests/test_lpdot.py
pulp/tests/test_pulp.py
pulp/tests/test_sparse.py
pulp-3.2.0.dist-info/METADATA
pulp-3.2.0.dist-info/WHEEL
pulp-3.2.0.dist-info/entry_points.txt
pulp-3.2.0.dist-info/top_level.txt
pulp-3.2.0.dist-info/RECORD
